fsm_admin/__init__.py
fsm_admin/mixins.py
fsm_admin/__pycache__/__init__.cpython-311.pyc
fsm_admin/__pycache__/__init__.cpython-38.pyc
fsm_admin/locale/de/LC_MESSAGES/django.mo
fsm_admin/locale/de/LC_MESSAGES/django.po
fsm_admin/locale/pt_BR/LC_MESSAGES/django.mo
fsm_admin/locale/pt_BR/LC_MESSAGES/django.po
fsm_admin/templates/fsm_admin/change_form.html
fsm_admin/templates/fsm_admin/fsm_submit_button.html
fsm_admin/templates/fsm_admin/fsm_submit_button_grappelli.html
fsm_admin/templates/fsm_admin/fsm_submit_button_suit.html
fsm_admin/templates/fsm_admin/fsm_submit_button_wpadmin.html
fsm_admin/templates/fsm_admin/fsm_submit_line.html
fsm_admin/templates/fsm_admin/fsm_submit_line_grappelli.html
fsm_admin/templates/fsm_admin/fsm_submit_line_suit.html
fsm_admin/templates/fsm_admin/fsm_submit_line_wpadmin.html
fsm_admin/templates/fsm_admin/fsm_transition_hints.html
fsm_admin/templates/fsm_admin/fsm_transition_hints_suit.html
fsm_admin/templatetags/__init__.py
fsm_admin/templatetags/fsm_admin.py
django_fsm_admin_v4-1.2.5.dist-info/LICENSE
django_fsm_admin_v4-1.2.5.dist-info/METADATA
django_fsm_admin_v4-1.2.5.dist-info/WHEEL
django_fsm_admin_v4-1.2.5.dist-info/top_level.txt
django_fsm_admin_v4-1.2.5.dist-info/RECORD
